{
  "name": "Synthetic Data Guardian Dev Environment",
  "dockerComposeFile": "../docker-compose.dev.yml",
  "service": "app",
  "workspaceFolder": "/workspace",
  "shutdownAction": "stopCompose",
  "features": {
    "ghcr.io/devcontainers/features/docker-in-docker:2": {},
    "ghcr.io/devcontainers/features/github-cli:1": {},
    "ghcr.io/devcontainers/features/node:1": {
      "version": "18"
    },
    "ghcr.io/devcontainers/features/python:1": {
      "version": "3.11"
    }
  },
  "customizations": {
    "vscode": {
      "extensions": [
        "ms-python.python",
        "ms-python.pylint",
        "ms-python.black-formatter",
        "bradlc.vscode-tailwindcss",
        "esbenp.prettier-vscode",
        "ms-vscode.vscode-eslint",
        "ms-vscode.vscode-typescript-next",
        "ms-vscode.test-adapter-converter",
        "hbenl.vscode-test-explorer",
        "ms-playwright.playwright",
        "redhat.vscode-yaml",
        "ms-vscode.vscode-json",
        "GitHub.copilot",
        "GitHub.copilot-chat",
        "ms-azuretools.vscode-docker",
        "ms-kubernetes-tools.vscode-kubernetes-tools",
        "humao.rest-client",
        "ms-vscode.hexeditor",
        "ms-vsliveshare.vsliveshare",
        "streetsidesoftware.code-spell-checker",
        "yzhang.markdown-all-in-one",
        "bierner.markdown-mermaid"
      ],
      "settings": {
        "python.defaultInterpreterPath": "/usr/local/bin/python",
        "python.formatting.provider": "black",
        "python.linting.enabled": true,
        "python.linting.pylintEnabled": true,
        "python.testing.pytestEnabled": true,
        "editor.formatOnSave": true,
        "editor.codeActionsOnSave": {
          "source.organizeImports": true,
          "source.fixAll.eslint": true
        },
        "files.exclude": {
          "**/.git": true,
          "**/.svn": true,
          "**/.hg": true,
          "**/CVS": true,
          "**/.DS_Store": true,
          "**/Thumbs.db": true,
          "**/__pycache__": true,
          "**/.pytest_cache": true,
          "**/node_modules": true,
          "**/dist": true,
          "**/coverage": true
        },
        "search.exclude": {
          "**/.git": true,
          "**/.svn": true,
          "**/.hg": true,
          "**/CVS": true,
          "**/.DS_Store": true,
          "**/Thumbs.db": true,
          "**/node_modules": true,
          "**/bower_components": true,
          "**/__pycache__": true,
          "**/.pytest_cache": true,
          "**/dist": true,
          "**/coverage": true
        }
      }
    }
  },
  "postCreateCommand": "npm install && pip install -r requirements-dev.txt && pre-commit install",
  "remoteUser": "vscode",
  "mounts": [
    "source=/var/run/docker.sock,target=/var/run/docker.sock,type=bind"
  ],
  "forwardPorts": [8080, 5432, 6379, 7687, 3000, 9090, 3001],
  "portsAttributes": {
    "8080": {
      "label": "API Server",
      "onAutoForward": "notify"
    },
    "5432": {
      "label": "PostgreSQL"
    },
    "6379": {
      "label": "Redis"
    },
    "7687": {
      "label": "Neo4j"
    },
    "3000": {
      "label": "Frontend Dev Server"
    },
    "9090": {
      "label": "Prometheus"
    },
    "3001": {
      "label": "Grafana"
    }
  }
}